tailsocket/__init__.py
tailsocket/application.py
tailsocket/errors.py
tailsocket/log.py
tailsocket/version.py
tailsocket/reader_registries/__init__.py
tailsocket/reader_registries/loop_reader_registry.py
tailsocket/reader_registries/notify_reader_registry.py
tailsocket/static/bin/448c34a56d699c29117adc64c43affeb.woff2
tailsocket/static/bin/89889688147bd7575d6327160d64e760.svg
tailsocket/static/bin/e18bbf611f2a2e43afc071aa2f4e1512.ttf
tailsocket/static/bin/f4769f9bdb7466be65088239c12046d1.eot
tailsocket/static/bin/fa2772327f55d8198301fdb8bcfc8158.woff
tailsocket/static/bin/style.css
tailsocket/static/bin/tailsocket.bundle.js
tailsocket/templates/base.html
tailsocket-0.1.1.dist-info/DESCRIPTION.rst
tailsocket-0.1.1.dist-info/METADATA
tailsocket-0.1.1.dist-info/RECORD
tailsocket-0.1.1.dist-info/WHEEL
tailsocket-0.1.1.dist-info/entry_points.txt
tailsocket-0.1.1.dist-info/metadata.json
tailsocket-0.1.1.dist-info/top_level.txt
tests/__init__.py
tests/application_test.py
tests/conftest.py
tests/reader_registry_test.py
