Metadata-Version: 2.0
Name: tailsocket
Version: 0.1.1
Summary: A WebSocket application to tail files.
Home-page: https://github.com/yeraydiazdiaz/tailsocket
Author: Yeray Diaz Diaz
Author-email: yeraydiazdiaz@gmail.com
License: MIT
Platform: UNKNOWN
Classifier: Development Status :: 4 - Beta
Classifier: Intended Audience :: Developers
Classifier: License :: OSI Approved :: MIT License
Classifier: Programming Language :: Python :: 3.5
Classifier: Topic :: System :: Logging
Requires-Dist: tornado (==4.4.1)
Requires-Dist: pyinotify (==0.9.6); sys_platform=='linux'
